square/__init__.py
square/__main__.py
preksha_square-1.0.0.dist-info/LICENSE
preksha_square-1.0.0.dist-info/METADATA
preksha_square-1.0.0.dist-info/WHEEL
preksha_square-1.0.0.dist-info/entry_points.txt
preksha_square-1.0.0.dist-info/top_level.txt
preksha_square-1.0.0.dist-info/RECORD
