Metadata-Version: 2.1
Name: preksha_square
Version: 1.0.0
Summary: It squares the number
Home-page: https://github.com/Preksha-Dadoo/preksha_square
Author: Preksha Dadoo
Author-email: pdadoo_be22@thapar.edu
License: MIT
Classifier: License :: OSI Approved :: MIT License
Classifier: Programming Language :: Python :: 3.6
Classifier: Programming Language :: Python :: 3.7
Classifier: Programming Language :: Python :: 3.8
License-File: LICENSE
